{
  "linked_tables": [
    {"name": "003 Hygienepläne Arbeitsschritte1", "linked_db": "C:\\OneDrive - Münstermann H. & I. GmbH\\Kunden\\Reinigungspläne.accdb", "linked_table": "003 Hygienepläne Arbeitsschritte"},
    {"name": "003 Hygienepläne1", "linked_db": "C:\\OneDrive - Münstermann H. & I. GmbH\\Kunden\\Reinigungspläne.accdb", "linked_table": "003 Hygienepläne"},
    {"name": "Kalender", "linked_db": "C:\\OneDrive - Münstermann H. & I. GmbH\\Büro\\Kalender\\Kalender 2026.accdb", "linked_table": "KalenderNW"},
    {"name": "KalenderWochen", "linked_db": "C:\\OneDrive - Münstermann H. & I. GmbH\\Büro\\Kalender\\Kalender 2026.accdb", "linked_table": "KalenderWochen"},
    {"name": "Kunden", "linked_db": "C:\\OneDrive - Münstermann H. & I. GmbH\\Personal\\Personal KG\\Adressen - Anschriften.accdb", "linked_table": "Kunden"},
    {"name": "tblSymboleGefahren", "linked_db": "C:\\OneDrive - Münstermann H. & I. GmbH\\Büro\\Reinigungsmittel\\Reinigungsmittel_2025.accdb", "linked_table": "tblSymboleGefahren"},
    {"name": "tblSymbolePSA", "linked_db": "C:\\OneDrive - Münstermann H. & I. GmbH\\Büro\\Reinigungsmittel\\Reinigungsmittel_2025.accdb", "linked_table": "tblSymbolePSA"},
    {"name": "tbl_RGM_Eigenschaften_2025", "linked_db": "C:\\OneDrive - Münstermann H. & I. GmbH\\Büro\\Reinigungsmittel\\Reinigungsmittel_2025.accdb", "linked_table": "tbl_RGM_Eigenschaften_2025"}
  ]
}
